sitorchtools/__init__.py
sitorchtools/dataloader.py
sitorchtools/earlystopping.py
sitorchtools/imbalanced.py
sitorchtools/img_folder_split.py
sitorchtools-0.0.1.dist-info/LICENSE
sitorchtools-0.0.1.dist-info/METADATA
sitorchtools-0.0.1.dist-info/WHEEL
sitorchtools-0.0.1.dist-info/top_level.txt
sitorchtools-0.0.1.dist-info/RECORD
