Metadata-Version: 2.1
Name: sitorchtools
Version: 0.0.1
Summary: A small package
Home-page: https://pypi.org/project/sitorchtools
Author: ulwan
Author-email: ulwan.nashihun@tiket.com
License: MIT
Keywords: pytorchtools,pytorch-early-stopping,image-dataloader,pytorch-imbalanced,data-scientist,deep-learning
Platform: UNKNOWN
Classifier: Programming Language :: Python :: 3
Classifier: License :: OSI Approved :: MIT License
Classifier: Operating System :: OS Independent
Classifier: Intended Audience :: Developers
Classifier: Topic :: Software Development :: Build Tools
Classifier: Topic :: Scientific/Engineering :: Artificial Intelligence
Classifier: Topic :: Scientific/Engineering :: Image Processing
Requires-Python: >=3.6
Requires-Dist: matplotlib (>=3.3.3)
Requires-Dist: numpy (>=1.19.4)
Requires-Dist: scikit-learn (>=0.24.0)
